<QuillLanguage lang="English" script="English" deffont="Arial" epsilon="">
	<tree key="&#151;" type="predictive">
		<node id="8">
			<split-rule>
				<rel-index>3</rel-index>
				<context-id>-1</context-id>
				<feature>('&#255;', 'Is letter &#255;?')</feature>
			</split-rule>
			<context-len>6</context-len>
			<terminal>False</terminal>
			<classes>[]</classes>
		</node>
		<node id="2">
			<split-rule>
				<rel-index>-1</rel-index>
				<context-id>-1</context-id>
				<feature>('&#239;', 'Is letter &#239;?')</feature>
			</split-rule>
			<context-len>6</context-len>
			<terminal>False</terminal>
			<classes>[]</classes>
		</node>
		<node id="1">
			<split-rule>
				<rel-index>0</rel-index>
				<context-id>-1</context-id>
				<feature>()</feature>
			</split-rule>
			<context-len>6</context-len>
			<terminal>True</terminal>
			<classes>[("m",673)]</classes>
		</node>
		<node id="6">
			<split-rule>
				<rel-index>-1</rel-index>
				<context-id>-1</context-id>
				<feature>('&#245;', 'Is letter &#245;?')</feature>
			</split-rule>
			<context-len>6</context-len>
			<terminal>False</terminal>
			<classes>[]</classes>
		</node>
		<node id="4">
			<split-rule>
				<rel-index>6</rel-index>
				<context-id>-1</context-id>
				<feature>('_', 'Is letter _?')</feature>
			</split-rule>
			<context-len>6</context-len>
			<terminal>False</terminal>
			<classes>[]</classes>
		</node>
		<node id="3">
			<split-rule>
				<rel-index>0</rel-index>
				<context-id>-1</context-id>
				<feature>()</feature>
			</split-rule>
			<context-len>6</context-len>
			<terminal>True</terminal>
			<classes>[("#",802)]</classes>
		</node>
		<node id="5">
			<split-rule>
				<rel-index>0</rel-index>
				<context-id>-1</context-id>
				<feature>()</feature>
			</split-rule>
			<context-len>6</context-len>
			<terminal>True</terminal>
			<classes>[("m",640)]</classes>
		</node>
		<node id="7">
			<split-rule>
				<rel-index>0</rel-index>
				<context-id>-1</context-id>
				<feature>()</feature>
			</split-rule>
			<context-len>6</context-len>
			<terminal>True</terminal>
			<classes>[("#",43175)]</classes>
		</node>
		<node id="10">
			<split-rule>
				<rel-index>-2</rel-index>
				<context-id>-1</context-id>
				<feature>('&#246;', 'Is letter &#246;?')</feature>
			</split-rule>
			<context-len>6</context-len>
			<terminal>False</terminal>
			<classes>[]</classes>
		</node>
		<node id="9">
			<split-rule>
				<rel-index>0</rel-index>
				<context-id>-1</context-id>
				<feature>()</feature>
			</split-rule>
			<context-len>6</context-len>
			<terminal>True</terminal>
			<classes>[("#",38888)]</classes>
		</node>
		<node id="12">
			<split-rule>
				<rel-index>-1</rel-index>
				<context-id>-1</context-id>
				<feature>('#', 'Is letter #?')</feature>
			</split-rule>
			<context-len>6</context-len>
			<terminal>False</terminal>
			<classes>[]</classes>
		</node>
		<node id="11">
			<split-rule>
				<rel-index>0</rel-index>
				<context-id>-1</context-id>
				<feature>()</feature>
			</split-rule>
			<context-len>6</context-len>
			<terminal>True</terminal>
			<classes>[("eh m",7298)]</classes>
		</node>
		<node id="14">
			<split-rule>
				<rel-index>-1</rel-index>
				<context-id>-1</context-id>
				<feature>('&#239;', 'Is letter &#239;?')</feature>
			</split-rule>
			<context-len>6</context-len>
			<terminal>False</terminal>
			<classes>[]</classes>
		</node>
		<node id="13">
			<split-rule>
				<rel-index>0</rel-index>
				<context-id>-1</context-id>
				<feature>()</feature>
			</split-rule>
			<context-len>6</context-len>
			<terminal>True</terminal>
			<classes>[("m",3165)]</classes>
		</node>
		<node id="16">
			<split-rule>
				<rel-index>-1</rel-index>
				<context-id>-1</context-id>
				<feature>('&#248;', 'Is letter &#248;?')</feature>
			</split-rule>
			<context-len>6</context-len>
			<terminal>False</terminal>
			<classes>[]</classes>
		</node>
		<node id="15">
			<split-rule>
				<rel-index>0</rel-index>
				<context-id>-1</context-id>
				<feature>()</feature>
			</split-rule>
			<context-len>6</context-len>
			<terminal>True</terminal>
			<classes>[("m",2637)]</classes>
		</node>
		<node id="28">
			<split-rule>
				<rel-index>-1</rel-index>
				<context-id>-1</context-id>
				<feature>('&#212;', 'Is letter &#212;?')</feature>
			</split-rule>
			<context-len>6</context-len>
			<terminal>False</terminal>
			<classes>[]</classes>
		</node>
		<node id="18">
			<split-rule>
				<rel-index>3</rel-index>
				<context-id>-1</context-id>
				<feature>('&#254;', 'Is letter &#254;?')</feature>
			</split-rule>
			<context-len>6</context-len>
			<terminal>False</terminal>
			<classes>[]</classes>
		</node>
		<node id="17">
			<split-rule>
				<rel-index>0</rel-index>
				<context-id>-1</context-id>
				<feature>()</feature>
			</split-rule>
			<context-len>6</context-len>
			<terminal>True</terminal>
			<classes>[("#",1199)]</classes>
		</node>
		<node id="22">
			<split-rule>
				<rel-index>-2</rel-index>
				<context-id>-1</context-id>
				<feature>('&#252;', 'Is letter &#252;?')</feature>
			</split-rule>
			<context-len>6</context-len>
			<terminal>False</terminal>
			<classes>[]</classes>
		</node>
		<node id="20">
			<split-rule>
				<rel-index>2</rel-index>
				<context-id>-1</context-id>
				<feature>('&#245;', 'Is letter &#245;?')</feature>
			</split-rule>
			<context-len>6</context-len>
			<terminal>False</terminal>
			<classes>[]</classes>
		</node>
		<node id="19">
			<split-rule>
				<rel-index>0</rel-index>
				<context-id>-1</context-id>
				<feature>()</feature>
			</split-rule>
			<context-len>6</context-len>
			<terminal>True</terminal>
			<classes>[("#",162)]</classes>
		</node>
		<node id="21">
			<split-rule>
				<rel-index>0</rel-index>
				<context-id>-1</context-id>
				<feature>()</feature>
			</split-rule>
			<context-len>6</context-len>
			<terminal>True</terminal>
			<classes>[("m",3609)]</classes>
		</node>
		<node id="26">
			<split-rule>
				<rel-index>-2</rel-index>
				<context-id>-1</context-id>
				<feature>('&#248;', 'Is letter &#248;?')</feature>
			</split-rule>
			<context-len>6</context-len>
			<terminal>False</terminal>
			<classes>[]</classes>
		</node>
		<node id="24">
			<split-rule>
				<rel-index>2</rel-index>
				<context-id>-1</context-id>
				<feature>('&#233;', 'Is letter &#233;?')</feature>
			</split-rule>
			<context-len>6</context-len>
			<terminal>False</terminal>
			<classes>[]</classes>
		</node>
		<node id="23">
			<split-rule>
				<rel-index>0</rel-index>
				<context-id>-1</context-id>
				<feature>()</feature>
			</split-rule>
			<context-len>6</context-len>
			<terminal>True</terminal>
			<classes>[("m",932)]</classes>
		</node>
		<node id="25">
			<split-rule>
				<rel-index>0</rel-index>
				<context-id>-1</context-id>
				<feature>()</feature>
			</split-rule>
			<context-len>6</context-len>
			<terminal>True</terminal>
			<classes>[("#",26)]</classes>
		</node>
		<node id="27">
			<split-rule>
				<rel-index>0</rel-index>
				<context-id>-1</context-id>
				<feature>()</feature>
			</split-rule>
			<context-len>6</context-len>
			<terminal>True</terminal>
			<classes>[("#",1739)]</classes>
		</node>
		<node id="30">
			<split-rule>
				<rel-index>-1</rel-index>
				<context-id>-1</context-id>
				<feature>('&#253;', 'Is letter &#253;?')</feature>
			</split-rule>
			<context-len>6</context-len>
			<terminal>False</terminal>
			<classes>[]</classes>
		</node>
		<node id="29">
			<split-rule>
				<rel-index>0</rel-index>
				<context-id>-1</context-id>
				<feature>()</feature>
			</split-rule>
			<context-len>6</context-len>
			<terminal>True</terminal>
			<classes>[("m-",1536)]</classes>
		</node>
		<node id="38">
			<split-rule>
				<rel-index>-1</rel-index>
				<context-id>-1</context-id>
				<feature>('&#245;', 'Is letter &#245;?')</feature>
			</split-rule>
			<context-len>6</context-len>
			<terminal>False</terminal>
			<classes>[]</classes>
		</node>
		<node id="32">
			<split-rule>
				<rel-index>2</rel-index>
				<context-id>-1</context-id>
				<feature>('&#242;', 'Is letter &#242;?')</feature>
			</split-rule>
			<context-len>6</context-len>
			<terminal>False</terminal>
			<classes>[]</classes>
		</node>
		<node id="31">
			<split-rule>
				<rel-index>0</rel-index>
				<context-id>-1</context-id>
				<feature>()</feature>
			</split-rule>
			<context-len>6</context-len>
			<terminal>True</terminal>
			<classes>[("m",604)]</classes>
		</node>
		<node id="36">
			<split-rule>
				<rel-index>2</rel-index>
				<context-id>-1</context-id>
				<feature>('&#213;', 'Is letter &#213;?')</feature>
			</split-rule>
			<context-len>6</context-len>
			<terminal>False</terminal>
			<classes>[]</classes>
		</node>
		<node id="34">
			<split-rule>
				<rel-index>6</rel-index>
				<context-id>-1</context-id>
				<feature>('&#206;', 'Is letter &#206;?')</feature>
			</split-rule>
			<context-len>6</context-len>
			<terminal>False</terminal>
			<classes>[]</classes>
		</node>
		<node id="33">
			<split-rule>
				<rel-index>0</rel-index>
				<context-id>-1</context-id>
				<feature>()</feature>
			</split-rule>
			<context-len>6</context-len>
			<terminal>True</terminal>
			<classes>[("#",2721)]</classes>
		</node>
		<node id="35">
			<split-rule>
				<rel-index>0</rel-index>
				<context-id>-1</context-id>
				<feature>()</feature>
			</split-rule>
			<context-len>6</context-len>
			<terminal>True</terminal>
			<classes>[("m",1799)]</classes>
		</node>
		<node id="37">
			<split-rule>
				<rel-index>0</rel-index>
				<context-id>-1</context-id>
				<feature>()</feature>
			</split-rule>
			<context-len>6</context-len>
			<terminal>True</terminal>
			<classes>[("#",1040)]</classes>
		</node>
		<node id="40">
			<split-rule>
				<rel-index>1</rel-index>
				<context-id>-1</context-id>
				<feature>('&#235;', 'Is letter &#235;?')</feature>
			</split-rule>
			<context-len>6</context-len>
			<terminal>False</terminal>
			<classes>[]</classes>
		</node>
		<node id="39">
			<split-rule>
				<rel-index>0</rel-index>
				<context-id>-1</context-id>
				<feature>()</feature>
			</split-rule>
			<context-len>6</context-len>
			<terminal>True</terminal>
			<classes>[("-m",109)]</classes>
		</node>
		<node id="41">
			<split-rule>
				<rel-index>0</rel-index>
				<context-id>-1</context-id>
				<feature>()</feature>
			</split-rule>
			<context-len>6</context-len>
			<terminal>True</terminal>
			<classes>[("#",26160)]</classes>
		</node>
	</tree>
</QuillLanguage>